{"expireTime":9007200905332911000,"key":"e08b68bed13ce44518ae0d603cb2b992","val":{"name":"IMAGE_PROCESSING","inputPaths":["/Users/baileylatimer/LocalSites/Clients/icymeta/src/images/sample-art.png"],"outputDir":"/Users/baileylatimer/LocalSites/Clients/icymeta/public/static/e45cf3ad5a1e709e1cf6ecc78b5b30bf","args":{"isLazy":false,"operations":[{"outputPath":"19ca5/sample-art.png","args":{"width":480,"cropFocus":17,"toFormat":"png","fit":"cover","background":"rgba(0,0,0,1)"}},{"outputPath":"d976a/sample-art.png","args":{"width":706,"cropFocus":17,"toFormat":"png","fit":"cover","background":"rgba(0,0,0,1)"}}],"pluginOptions":{"base64Width":20,"forceBase64Format":"","useMozJpeg":false,"stripMetadata":true,"lazyImageGeneration":true,"defaultQuality":50,"failOnError":true,"plugins":[]}}}}